trackio/CHANGELOG.md
trackio/README.md
trackio/__init__.py
trackio/api.py
trackio/cli.py
trackio/cli_helpers.py
trackio/commit_scheduler.py
trackio/context_vars.py
trackio/deploy.py
trackio/dummy_commit_scheduler.py
trackio/gpu.py
trackio/histogram.py
trackio/imports.py
trackio/package.json
trackio/py.typed
trackio/run.py
trackio/sqlite_storage.py
trackio/table.py
trackio/typehints.py
trackio/utils.py
trackio/assets/badge.png
trackio/assets/trackio_logo_dark.png
trackio/assets/trackio_logo_light.png
trackio/assets/trackio_logo_old.png
trackio/assets/trackio_logo_type_dark.png
trackio/assets/trackio_logo_type_dark_transparent.png
trackio/assets/trackio_logo_type_light.png
trackio/assets/trackio_logo_type_light_transparent.png
trackio/media/__init__.py
trackio/media/audio.py
trackio/media/image.py
trackio/media/media.py
trackio/media/utils.py
trackio/media/video.py
trackio/ui/__init__.py
trackio/ui/files.py
trackio/ui/fns.py
trackio/ui/main.py
trackio/ui/media_page.py
trackio/ui/run_detail.py
trackio/ui/runs.py
trackio/ui/system_page.py
trackio/ui/components/colored_checkbox.py
trackio/ui/components/colored_dropdown.py
trackio/ui/components/runs_table.py
trackio/ui/helpers/run_selection.py
trackio-0.15.0.dist-info/METADATA
trackio-0.15.0.dist-info/WHEEL
trackio-0.15.0.dist-info/entry_points.txt
trackio-0.15.0.dist-info/licenses/LICENSE
trackio-0.15.0.dist-info/RECORD
