Metadata-Version: 2.4
Name: trackio
Version: 0.15.0
Summary: A lightweight, local-first, and free experiment tracking library built on top of Hugging Face Datasets and Spaces.
Project-URL: homepage, https://github.com/gradio-app/trackio
Project-URL: repository, https://github.com/gradio-app/trackio
Author-email: Abubakar Abid <abubakar@huggingface.co>, Zach Nation <zach@huggingface.co>
License-File: LICENSE
Classifier: License :: OSI Approved :: MIT License
Classifier: Operating System :: OS Independent
Classifier: Programming Language :: Python :: 3
Requires-Python: >=3.10
Requires-Dist: gradio[oauth]<7.0.0,>=6.3.0
Requires-Dist: huggingface-hub<2.0.0
Requires-Dist: numpy<3.0.0
Requires-Dist: orjson<4.0.0,>=3.0
Requires-Dist: pandas<3.0.0
Requires-Dist: pillow<12.0.0
Requires-Dist: plotly<7.0.0,>=6.0.0
Requires-Dist: pydub<1.0.0
Requires-Dist: tomli>=2.0.0; python_version < '3.11'
Provides-Extra: dev
Requires-Dist: playwright<2.0.0,>=1.40.0; extra == 'dev'
Requires-Dist: pytest-playwright<1.0.0,>=0.7.0; extra == 'dev'
Requires-Dist: pytest<9.0.0,>=8.0.0; extra == 'dev'
Requires-Dist: ruff==0.9.3; extra == 'dev'
Provides-Extra: gpu
Requires-Dist: nvidia-ml-py>=12.0.0; extra == 'gpu'
Provides-Extra: spaces
Requires-Dist: pyarrow>=21.0; extra == 'spaces'
Provides-Extra: tensorboard
Requires-Dist: tbparse==0.0.9; extra == 'tensorboard'
Requires-Dist: tensorboardx<3.0.0,>=2.0.0; extra == 'tensorboard'
